{
  "urls": [
    {
      "link": "/",
      "name": "front"
    },
    {
      "link": "/payments/",
      "name": "payments"
    },
    {
      "link": "/team/",
      "name": "team"
    },
    {
      "link": "/calculator/",
      "name": "calculator"
    },
    {
      "link": "/inner/",
      "name": "inner"
    },
    {
      "link": "/catalog/inner2/",
      "name": "inner2"
    },
    {
      "link": "/installation/",
      "name": "installation"
    },
    {
      "link": "/contacts/",
      "name": "contacts"
    },
    {
      "link": "/catalog/",
      "name": "catalog"
    }
  ]
}
